setup.py
django_sse/__init__.py
django_sse/redisqueue.py
django_sse/views.py
django_sse.egg-info/PKG-INFO
django_sse.egg-info/SOURCES.txt
django_sse.egg-info/dependency_links.txt
django_sse.egg-info/not-zip-safe
django_sse.egg-info/requires.txt
django_sse.egg-info/top_level.txt