Metadata-Version: 1.1
Name: django-sse
Version: 0.4
Summary: HTML5 Server-Side Events for Django 1.3+
Home-page: https://github.com/niwibe/django-sse
Author: Andrei Antoukh
Author-email: niwi@niwi.be
License: BSD
Platform: OS Independent
Classifier: Development Status :: 4 - Beta
Classifier: Framework :: Django
Classifier: Intended Audience :: Developers
Classifier: License :: OSI Approved :: BSD License
Classifier: Operating System :: OS Independent
Classifier: Programming Language :: Python
Classifier: Programming Language :: Python :: 2.7
Classifier: Topic :: Internet :: WWW/HTTP
